examples/__init__.py
examples/auth_service/__init__.py
examples/auth_service/app.py
sbus/__init__.py
sbus/exceptions.py
sbus/models.py
sbus/router.py
sbus/sbus.py
sbus/serializer.py
sbus/subscribers.py
sbus/utils.py
sbus/transports/__init__.py
sbus/transports/aiopika.py
sbus/transports/base.py
sbus-0.2.5.dist-info/METADATA
sbus-0.2.5.dist-info/RECORD
sbus-0.2.5.dist-info/WHEEL
sbus-0.2.5.dist-info/top_level.txt
tests/__init__.py
tests/conftest.py
tests/test_reader.py
tests/test_router.py
tests/test_sbus.py
tests/utils.py
tests/subscribers/__init__.py
tests/transports/__init__.py
