Metadata-Version: 1.0
Name: sbus
Version: 0.2.5
Summary: Pub/sub abstraction for aioamqp
Home-page: https://github.com/dyuuus/sbus
Author: Andrey Zdanchuk
Author-email: dyuuus@gmail.com
License: BSD License
Platform: UNKNOWN
